<?xml version="1.0" encoding="UTF-8"?>
<Sagemobile>
  <Encabezado Cia="02" Otra_Cia="02" Pedido="181249" Cliente="0036" Nombre="Jaime Alfaro" Fecha="21/08/2023" Tipo="1" Direccion="Avenida Samuel Lewis, Calle 54, Edif. Afra " Direccion2="Panama Panamá Panamá City 62557" AgenteEmbarcador="" Observaciones="SS24-Q2-RP-05-INTER MIAMI-MAURICIO CARRANZA" ResponsablePedido="" ResponsableImportacion="" Contacto="Jaime Alfaro" OtrasInstrucciones="" Noordencompra="" TipoEntrega="1" Sustitucion="" Courrier="" Seguro="" Empaque="" Marca1="" Marca2="" Marca3="" Marca4="">
    <Linea Producto="MIATS523201-WH1" Color="WH1" Cantidad="7" size_S="28" size_M="56" size_L="56" size_XL="28" Unit_Box_Qty="24" Total_Box_Qty="168" Precio="6.5"></Linea>
    <Linea Producto="MIATS523201-PK1" Color="PK1" Cantidad="8" size_S="32" size_M="64" size_L="64" size_XL="32" Unit_Box_Qty="24" Total_Box_Qty="192" Precio="6.5"></Linea>
    <Linea Producto="MIATS523202-BK1" Color="BK1" Cantidad="7" size_S="28" size_M="56" size_L="56" size_XL="28" Unit_Box_Qty="24" Total_Box_Qty="168" Precio="6.5"></Linea>
    <Linea Producto="MIAHD523201-OW1" Color="OW1" Cantidad="7" size_S="28" size_M="56" size_L="56" size_XL="28" Unit_Box_Qty="24" Total_Box_Qty="168" Precio="15"></Linea>
    <Linea Producto="MIACA523201-BK1" Color="BK1" Cantidad="6" size_OS="144" Unit_Box_Qty="24" Total_Box_Qty="144" Precio="7.5"></Linea>
    <Linea Producto="MIACA523201-OW1" Color="OW1" Cantidad="6" size_OS="144" Unit_Box_Qty="24" Total_Box_Qty="144" Precio="7.5"></Linea>
  </Encabezado>
</Sagemobile>
